wanyi_today/__init__.py
wanyi_today/__main__.py
wanyi_today/main.py
wanyi_today-0.1.7.dist-info/METADATA
wanyi_today-0.1.7.dist-info/WHEEL
wanyi_today-0.1.7.dist-info/entry_points.txt
wanyi_today-0.1.7.dist-info/licenses/LICENSE
wanyi_today-0.1.7.dist-info/RECORD
