Metadata-Version: 2.4
Name: wanyi-today
Version: 0.1.7
Summary: A FastMCP demo server with number addition and mystical answer book tools
Project-URL: Homepage, https://github.com/Ryan7t/wanyi-today
Project-URL: Repository, https://github.com/Ryan7t/wanyi-today
Project-URL: Issues, https://github.com/Ryan7t/wanyi-today/issues
Author-email: Your Name <your.email@example.com>
License: MIT
License-File: LICENSE
Keywords: demo,fastmcp,mcp,server
Classifier: Development Status :: 3 - Alpha
Classifier: Intended Audience :: Developers
Classifier: License :: OSI Approved :: MIT License
Classifier: Programming Language :: Python :: 3
Classifier: Programming Language :: Python :: 3.8
Classifier: Programming Language :: Python :: 3.9
Classifier: Programming Language :: Python :: 3.10
Classifier: Programming Language :: Python :: 3.11
Classifier: Programming Language :: Python :: 3.12
Requires-Python: >=3.8
Requires-Dist: mcp>=1.2.0
